speedybotdev/__init__.py
speedybotdev/cli.py
speedybotdev/consts.py
speedybotdev/repo.py
speedybotdev/speedybot.py
speedybotdev/speedycard.py
speedybotdev-0.2.8.dist-info/METADATA
speedybotdev-0.2.8.dist-info/WHEEL
speedybotdev-0.2.8.dist-info/entry_points.txt
speedybotdev-0.2.8.dist-info/top_level.txt
speedybotdev-0.2.8.dist-info/RECORD
