Metadata-Version: 2.1
Name: speedybotdev
Version: 0.2.8
Summary: A bot framework
Requires-Python: >=3.11
